{
  "version": "7",
  "dialect": "postgresql",
  "entries": [
    {
      "idx": 0,
      "version": "7",
      "when": 1745213595423,
      "tag": "0000_known_photon",
      "breakpoints": true
    },
    {
      "idx": 1,
      "version": "7",
      "when": 1745214711256,
      "tag": "0001_cute_wallop",
      "breakpoints": true
    },
    {
      "idx": 2,
      "version": "7",
      "when": 1745645696630,
      "tag": "0002_short_garia",
      "breakpoints": true
    },
    {
      "idx": 3,
      "version": "7",
      "when": 1745651416558,
      "tag": "0003_strange_impossible_man",
      "breakpoints": true
    },
    {
      "idx": 4,
      "version": "7",
      "when": 1745652912323,
      "tag": "0004_conscious_thor_girl",
      "breakpoints": true
    }
  ]
}